[
{"city": "Taiwan", "name": "Betty Ford", "instagram": "bettyford_"},
{"city": "Taiwan", "name": "Christine Chang", "instagram": "changcc72"},
{"city": "Taiwan", "name": "James Chen", "instagram": "supletsgoplay"},
{"city": "Taiwan", "name": "Jazzmine Yu", "instagram": "jazzmine928"},
{"city": "Taiwan", "name": "Jen Hau", "instagram": "jenhau"},
{"city": "Taiwan", "name": "Jessi Fu", "instagram": "j3ssiw_3d"},
{"city": "Taiwan", "name": "Joseph Sona Eyambe", "instagram": "stalksona"},
{"city": "Taiwan", "name": "Jovi Lo", "instagram": "jomavi3"},
{"city": "Taiwan", "name": "Jun Lee", "instagram": "junlee108"},
{"city": "Taiwan", "name": "Kingson Chou", "instagram": "kingson1231"},
{"city": "Taiwan", "name": "Kiya Wei", "instagram": "kiyaandjames"},
{"city": "Singapore", "name": "Aidan\tChemaly", "instagram": "aidanchemaly"},
{"city": "Singapore", "name": "Brandon Chong", "instagram": "branstands"},
{"city": "Singapore", "name": "Bronson Chan", "instagram": "bc_flowstate"},
{"city": "Singapore", "name": "Dawn Sim", "instagram": "thatmomoffour"},
{"city": "Singapore", "name": "Elizabeth Wright", "instagram": "lizziewrighty"},
{"city": "Singapore", "name": "Fiona Siew", "instagram": "fearlessfi"},
{"city": "Singapore", "name": "Gavin Ong", "instagram": "gavong"},
{"city": "Singapore", "name": "Jessica Sinclair", "instagram": "jessicasinclairyoga"},
{"city": "Singapore", "name": "Linda Tang", "instagram": "linda_tang"},
{"city": "Singapore", "name": "Lindsey Larkin", "instagram": "lindsey_larkin"},
{"city": "Singapore", "name": "Ling Er Choo", "instagram": "lingultragal"}
]